AUTHORS.rst
CONTRIBUTING.rst
HISTORY.rst
LICENSE
MANIFEST.in
README.rst
setup.py
wikipediabase/__init__.py
wikipediabase/context.py
wikipediabase/functions.py
wikipediabase/skin.py
wikipediabase.egg-info/PKG-INFO
wikipediabase.egg-info/SOURCES.txt
wikipediabase.egg-info/dependency_links.txt
wikipediabase.egg-info/not-zip-safe
wikipediabase.egg-info/requires.txt
wikipediabase.egg-info/top_level.txt