Metadata-Version: 1.1
Name: wikipediabase
Version: 0.1.0
Summary: "Wikipedia scraper done in python for use in start.mit.edu"
Home-page: https://github.com/fakedrake/wikipediabase
Author: Chris Perivolaropoulos
Author-email: darksaga2006@gmail.com
License: BSD
Keywords: wikipediabase
Platform: UNKNOWN
Classifier: Development Status :: 2 - Pre-Alpha
Classifier: Intended Audience :: Developers
Classifier: License :: OSI Approved :: BSD License
Classifier: Natural Language :: English
Classifier: Programming Language :: Python :: 2
Classifier: Programming Language :: Python :: 2.6
Classifier: Programming Language :: Python :: 2.7
Classifier: Programming Language :: Python :: 3
Classifier: Programming Language :: Python :: 3.3
